scripts/audio_batch_analysis.py
scripts/enhance_voice.py
tests/conftest.py
tests/test_app_args.py
tests/test_audio_base_app.py
tests/test_audio_pipeline.py
tests/test_consumer_thread.py
tests/test_hardware_config.py
tests/test_listener_thread.py
tests/test_thread_app.py
tests/core/conftest.py
tests/core/test_audio_metrics.py
tests/core/test_datetime_stamp.py
tests/hardwares/conftest.py
tests/hardwares/test_selector.py
tests/integration/test_zmq_topology.py
tests/sinks/conftest.py
tests/transformers/test_calibrator_cache_strategy.py
tests/transformers/test_calibrator_transformer.py
tests/transports/test_queue_transport.py
tests/transports/test_zmq_transport.py
umik_base_app/__init__.py
umik_base_app/_version.py
umik_base_app/app_args.py
umik_base_app/app_config.py
umik_base_app/audio_base_app.py
umik_base_app/audio_pipeline.py
umik_base_app/base_thread_app.py
umik_base_app/consumer_thread.py
umik_base_app/create_transport.py
umik_base_app/hardware_config.py
umik_base_app/listener_thread.py
umik_base_app/settings.py
umik_base_app/apps/basic_recorder.py
umik_base_app/apps/list_audio_devices.py
umik_base_app/apps/metrics_analyzer.py
umik_base_app/apps/metrics_plotter.py
umik_base_app/apps/real_time_meter.py
umik_base_app/apps/umik1_calibrator.py
umik_base_app/core/audio_metrics.py
umik_base_app/core/datetime_stamp.py
umik_base_app/core/operational_mode.py
umik_base_app/hardwares/selector.py
umik_base_app/sinks/recorder_adapter.py
umik_base_app/sinks/recorder_sink.py
umik_base_app/sinks/sinks_protocol.py
umik_base_app/transformers/calibrator_adapter.py
umik_base_app/transformers/calibrator_cache_strategy.py
umik_base_app/transformers/calibrator_transformer.py
umik_base_app/transformers/transformers_protocol.py
umik_base_app/transports/base_transport.py
umik_base_app/transports/queue_transport.py
umik_base_app/transports/zmq_transport.py
umik_base_app-0.4.3a1.dev0.dist-info/licenses/LICENSE
umik_base_app-0.4.3a1.dev0.dist-info/METADATA
umik_base_app-0.4.3a1.dev0.dist-info/WHEEL
umik_base_app-0.4.3a1.dev0.dist-info/entry_points.txt
umik_base_app-0.4.3a1.dev0.dist-info/top_level.txt
umik_base_app-0.4.3a1.dev0.dist-info/RECORD
