Metadata-Version: 2.4
Name: umik-base-app
Version: 0.4.3a1.dev0
Summary: Base utilities for working with the Umik-1 microphone in Python applications.
Author-email: Daniel Collier <danielfcollier@gmail.com>
Project-URL: Homepage, https://github.com/danielfcollier/py-umik-base-app
Project-URL: Bug Tracker, https://github.com/danielfcollier/py-umik-base-app/issues
Requires-Python: <3.14,>=3.9
License-File: LICENSE
Requires-Dist: numpy>=1.26.0
Requires-Dist: scipy>=1.12.0
Requires-Dist: pydantic>=2.5.0
Requires-Dist: sounddevice>=0.4.6
Requires-Dist: librosa>=0.10.0
Requires-Dist: pyloudnorm>=0.1.1
Requires-Dist: pydantic-settings>=2.1.0
Requires-Dist: pydub>=0.25.1
Requires-Dist: noisereduce>=3.0.0
Requires-Dist: matplotlib>=3.9.0
Requires-Dist: pandas>=2.2.0
Requires-Dist: python-dotenv>=1.2.1
Requires-Dist: pyzmq>=24.0.0
Provides-Extra: dev
Requires-Dist: ruff>=0.1.0; extra == "dev"
Requires-Dist: mypy>=1.4.0; extra == "dev"
Requires-Dist: pytest>=7.4.0; extra == "dev"
Requires-Dist: pytest-cov>=4.0.0; extra == "dev"
Requires-Dist: pytest-timeout>=2.1.0; extra == "dev"
Dynamic: license-file
